IntelMapClient/__init__.py
IntelMapClient/api.py
IntelMapClient/client.py
IntelMapClient/errors.py
IntelMapClient/types.py
IntelMapClient/utils.py
intel_map_client-0.2.3.dist-info/LICENSE
intel_map_client-0.2.3.dist-info/METADATA
intel_map_client-0.2.3.dist-info/WHEEL
intel_map_client-0.2.3.dist-info/top_level.txt
intel_map_client-0.2.3.dist-info/RECORD
