Metadata-Version: 2.1
Name: intel-map-client
Version: 0.2.3
Summary: An API client for Intel Map
Home-page: https://github.com/67au/intel-map-client
Maintainer: 67au
Maintainer-email: oyy6745@gmail.com
License: MIT License
Classifier: Programming Language :: Python :: 3.7
Classifier: Programming Language :: Python :: 3.8
Classifier: Programming Language :: Python :: 3.9
Classifier: License :: OSI Approved :: MIT License
Requires-Python: >=3.7
License-File: LICENSE
Requires-Dist: httpx
Requires-Dist: httpx-socks[asyncio]
